ndop/__init__.py
ndop_downloader-0.1.8.data/scripts/ndop
ndop_downloader-0.1.8.dist-info/LICENSE
ndop_downloader-0.1.8.dist-info/METADATA
ndop_downloader-0.1.8.dist-info/WHEEL
ndop_downloader-0.1.8.dist-info/top_level.txt
ndop_downloader-0.1.8.dist-info/RECORD
