Metadata-Version: 2.1
Name: ndop-downloader
Version: 0.1.8
Summary: NDOP Downloader is an application for downloading of records of occurence from official database of the Nature Conservation Agency of the Czech Republic (Nálezová databáze Agentury ochrany přírody a krajiny ČR - NDOP - AOPK).
Home-page: https://github.com/OpenGeoLabs/qgis-ndop-downloader
Author: Oto Kaláb
Author-email: oto.kalab@opengeolabs.cz
Maintainer: Oto Kaláb
Maintainer-email: oto.kalab@opengeolabs.cz
License: GNU/GPL3
Keywords: GIS,AOPK,ecology,species occurences,NDOP,Czech Republic,nálezová databáze
Platform: UNKNOWN
Classifier: Development Status :: 4 - Beta
Classifier: Environment :: Console
Classifier: Intended Audience :: Science/Research
Classifier: License :: OSI Approved :: GNU General Public License v3 (GPLv3)
Classifier: Natural Language :: Czech
Classifier: Operating System :: POSIX :: Linux
Classifier: Programming Language :: Python :: 3
Requires-Dist: requests (==2.21.0)
Requires-Dist: Fiona (==1.8.4)
